[
  {
    "arguments": [
      "/usr/bin/gcc",
      "-c",
      "-g",
      "-I",
      "lib",
      "-o",
      "obj/liman.o",
      "src/liman.c"
    ],
    "directory": "/home/carlos/repos/liman",
    "file": "/home/carlos/repos/liman/src/liman.c",
    "output": "/home/carlos/repos/liman/obj/liman.o"
  },
  {
    "arguments": [
      "/usr/bin/gcc",
      "-c",
      "-g",
      "-I",
      "lib",
      "-o",
      "obj/main.o",
      "src/main.c"
    ],
    "directory": "/home/carlos/repos/liman",
    "file": "/home/carlos/repos/liman/src/main.c",
    "output": "/home/carlos/repos/liman/obj/main.o"
  },
  {
    "arguments": [
      "/usr/bin/gcc",
      "-c",
      "-g",
      "-I",
      "lib",
      "-o",
      "obj/container/CircularLinkedList.o",
      "src/container/CircularLinkedList.c"
    ],
    "directory": "/home/carlos/repos/liman",
    "file": "/home/carlos/repos/liman/src/container/CircularLinkedList.c",
    "output": "/home/carlos/repos/liman/obj/container/CircularLinkedList.o"
  },
  {
    "arguments": [
      "/usr/bin/gcc",
      "-c",
      "-g",
      "-I",
      "lib",
      "-o",
      "obj/container/Tree.o",
      "src/container/Tree.c"
    ],
    "directory": "/home/carlos/repos/liman",
    "file": "/home/carlos/repos/liman/src/container/Tree.c",
    "output": "/home/carlos/repos/liman/obj/container/Tree.o"
  },
  {
    "arguments": [
      "/usr/bin/gcc",
      "-c",
      "-g",
      "-I",
      "lib",
      "-o",
      "obj/types/Bitmap.o",
      "src/types/Bitmap.c"
    ],
    "directory": "/home/carlos/repos/liman",
    "file": "/home/carlos/repos/liman/src/types/Bitmap.c",
    "output": "/home/carlos/repos/liman/obj/types/Bitmap.o"
  },
  {
    "arguments": [
      "/usr/bin/gcc",
      "-c",
      "-g",
      "-I",
      "lib",
      "-o",
      "obj/types/Caracter.o",
      "src/types/Caracter.c"
    ],
    "directory": "/home/carlos/repos/liman",
    "file": "/home/carlos/repos/liman/src/types/Caracter.c",
    "output": "/home/carlos/repos/liman/obj/types/Caracter.o"
  },
  {
    "arguments": [
      "/usr/bin/gcc",
      "-c",
      "-g",
      "-I",
      "lib",
      "-o",
      "obj/types/HuffmanTree.o",
      "src/types/HuffmanTree.c"
    ],
    "directory": "/home/carlos/repos/liman",
    "file": "/home/carlos/repos/liman/src/types/HuffmanTree.c",
    "output": "/home/carlos/repos/liman/obj/types/HuffmanTree.o"
  },
  {
    "arguments": [
      "/usr/bin/gcc",
      "-c",
      "-g",
      "-I",
      "lib",
      "-o",
      "obj/types/TreeList.o",
      "src/types/TreeList.c"
    ],
    "directory": "/home/carlos/repos/liman",
    "file": "/home/carlos/repos/liman/src/types/TreeList.c",
    "output": "/home/carlos/repos/liman/obj/types/TreeList.o"
  },
  {
    "arguments": [
      "/usr/bin/gcc",
      "-c",
      "-g",
      "-I",
      "lib",
      "-o",
      "obj/utils/bits.o",
      "src/utils/bits.c"
    ],
    "directory": "/home/carlos/repos/liman",
    "file": "/home/carlos/repos/liman/src/utils/bits.c",
    "output": "/home/carlos/repos/liman/obj/utils/bits.o"
  },
  {
    "arguments": [
      "/usr/bin/gcc",
      "-c",
      "-g",
      "-I",
      "lib",
      "-o",
      "obj/utils/file.o",
      "src/utils/file.c"
    ],
    "directory": "/home/carlos/repos/liman",
    "file": "/home/carlos/repos/liman/src/utils/file.c",
    "output": "/home/carlos/repos/liman/obj/utils/file.o"
  }
]
